neris_api_client/__init__.py
neris_api_client/client.py
neris_api_client/config.py
neris_api_client/models.py
neris_api_client-1.5.1.dist-info/licenses/LICENSE
neris_api_client-1.5.1.dist-info/METADATA
neris_api_client-1.5.1.dist-info/WHEEL
neris_api_client-1.5.1.dist-info/top_level.txt
neris_api_client-1.5.1.dist-info/RECORD
