Metadata-Version: 2.4
Name: neris_api_client
Version: 1.5.1
Summary: NERIS API Client
Author-email: Ben Coleman <ben.coleman@ul.org>, Joseph Pagani <joseph.pagani@ul.org>
Project-URL: Homepage, https://github.com/ulfsri/neris-api-client
Project-URL: Issues, https://neris.atlassian.net/servicedesk/customer/portal/3/group/3/create/10027
Classifier: Programming Language :: Python :: 3
Classifier: License :: OSI Approved :: MIT License
Classifier: Operating System :: OS Independent
Requires-Python: >=3.8
License-File: LICENSE
Requires-Dist: requests
Requires-Dist: pydantic[email]>=2
Requires-Dist: python-dotenv
Dynamic: license-file
